python_htmlinfo/__init__.py
python_htmlinfo/info.py
python_htmlinfo-0.1.7.dist-info/METADATA
python_htmlinfo-0.1.7.dist-info/WHEEL
python_htmlinfo-0.1.7.dist-info/entry_points.txt
python_htmlinfo-0.1.7.dist-info/top_level.txt
python_htmlinfo-0.1.7.dist-info/RECORD
