Metadata-Version: 2.4
Name: python-htmlinfo
Version: 0.1.7
Summary: Beautiful HTML version of phpinfo(), but for Python.
Home-page: https://pypi.org/project/python-htmlinfo/
Author: ATRCORE-UA
Author-email: mail@atrcore.pp.ua
License: MIT
Project-URL: Source, https://github.com/ATRCORE-UA/python-htmlinfo
Keywords: python,info,phpinfo,html,system,environment
Classifier: Programming Language :: Python :: 3
Classifier: License :: OSI Approved :: MIT License
Classifier: Operating System :: OS Independent
Requires-Python: >=3.6
Requires-Dist: setuptools
Dynamic: author
Dynamic: author-email
Dynamic: classifier
Dynamic: description
Dynamic: description-content-type
Dynamic: home-page
Dynamic: keywords
Dynamic: license
Dynamic: project-url
Dynamic: requires-dist
Dynamic: requires-python
Dynamic: summary
